Database_Updates/__init__.py
Database_Updates/Hockey/__init__.py
Database_Updates/Hockey/update_GamesHockey.py
Database_Updates/Hockey/update_SpecificHockey.py
Database_Updates/Hockey/update_allOdds.py
pySports_Arbitrage-0.1.dev1.dist-info/METADATA
pySports_Arbitrage-0.1.dev1.dist-info/WHEEL
pySports_Arbitrage-0.1.dev1.dist-info/top_level.txt
pySports_Arbitrage-0.1.dev1.dist-info/RECORD
