Metadata-Version: 2.1
Name: pySports-Arbitrage
Version: 0.1.dev1
Author: Phil Rongo
Requires-Python: >=3.6
